inflator/__init__.py
inflator/__main__.py
inflator/cookies.py
inflator/gtp.py
inflator/install.py
inflator/new.py
inflator/package.py
inflator/parse.py
inflator/sync.py
inflator/toml.py
inflator/util.py
inflator-1.0.9.dist-info/METADATA
inflator-1.0.9.dist-info/WHEEL
inflator-1.0.9.dist-info/entry_points.txt
inflator-1.0.9.dist-info/top_level.txt
inflator-1.0.9.dist-info/RECORD
