Metadata-Version: 2.4
Name: inflator
Version: 1.0.9
Summary: Inflates gobos. A goboscript package manager.
Author: faretek1
Project-URL: Source, https://github.com/inflated-goboscript/inflator
Project-URL: Documentation, https://inflated-goboscript.github.io/inflator/
Project-URL: Homepage, https://inflated-goboscript.github.io/inflator/
Keywords: goboscript
Requires-Dist: setuptools~=80.9.0
Requires-Dist: furl~=2.1.4
Requires-Dist: httpx~=0.28.1
Requires-Dist: python-slugify~=8.0.4
Requires-Dist: pygithub~=2.8.1
Dynamic: author
Dynamic: description
Dynamic: description-content-type
Dynamic: keywords
Dynamic: project-url
Dynamic: requires-dist
Dynamic: summary
